{
    "description": "",
    "tags": [],
    "size": {
        "height": 720,
        "width": 1280
    },
    "objects": [
        {
            "description": "",
            "geometryType": "rectangle",
            "labelerLogin": "ewwong2@dons.usfca.edu",
            "createdAt": "2020-04-10T02:48:16.339Z",
            "updatedAt": "2020-04-10T02:48:21.792Z",
            "tags": [],
            "classTitle": "cucumber_fruit",
            "points": {
                "exterior": [
                    [
                        750,
                        153
                    ],
                    [
                        820,
                        332
                    ]
                ],
                "interior": []
            }
        },
        {
            "description": "",
            "geometryType": "rectangle",
            "labelerLogin": "ewwong2@dons.usfca.edu",
            "createdAt": "2020-04-10T02:48:18.632Z",
            "updatedAt": "2020-04-10T02:48:21.792Z",
            "tags": [],
            "classTitle": "cucumber_fruit",
            "points": {
                "exterior": [
                    [
                        699,
                        0
                    ],
                    [
                        810,
                        123
                    ]
                ],
                "interior": []
            }
        },
        {
            "description": "",
            "geometryType": "rectangle",
            "labelerLogin": "ewwong2@dons.usfca.edu",
            "createdAt": "2020-04-10T02:48:21.573Z",
            "updatedAt": "2020-04-10T02:48:21.573Z",
            "tags": [],
            "classTitle": "cucumber_fruit_unripe",
            "points": {
                "exterior": [
                    [
                        876,
                        90
                    ],
                    [
                        917,
                        186
                    ]
                ],
                "interior": []
            }
        }
    ]
}