{
    "description": "",
    "tags": [],
    "size": {
        "height": 864,
        "width": 1300
    },
    "objects": [
        {
            "description": "",
            "geometryType": "rectangle",
            "labelerLogin": "ewwong2@dons.usfca.edu",
            "createdAt": "2020-04-25T17:46:15.030Z",
            "updatedAt": "2020-04-25T17:46:15.030Z",
            "tags": [],
            "classTitle": "cucumber_flower",
            "points": {
                "exterior": [
                    [
                        496,
                        125
                    ],
                    [
                        866,
                        487
                    ]
                ],
                "interior": []
            }
        }
    ]
}