{
    "description": "",
    "tags": [],
    "size": {
        "height": 720,
        "width": 1280
    },
    "objects": [
        {
            "description": "",
            "geometryType": "rectangle",
            "labelerLogin": "ewwong2@dons.usfca.edu",
            "createdAt": "2020-05-01T07:15:37.462Z",
            "updatedAt": "2020-05-01T07:15:55.801Z",
            "tags": [],
            "classTitle": "cucumber_flower",
            "points": {
                "exterior": [
                    [
                        294,
                        426
                    ],
                    [
                        403,
                        512
                    ]
                ],
                "interior": []
            }
        },
        {
            "description": "",
            "geometryType": "rectangle",
            "labelerLogin": "ewwong2@dons.usfca.edu",
            "createdAt": "2020-05-01T07:15:41.253Z",
            "updatedAt": "2020-05-01T07:15:55.801Z",
            "tags": [],
            "classTitle": "cucumber_fruit",
            "points": {
                "exterior": [
                    [
                        326,
                        291
                    ],
                    [
                        399,
                        425
                    ]
                ],
                "interior": []
            }
        },
        {
            "description": "",
            "geometryType": "rectangle",
            "labelerLogin": "ewwong2@dons.usfca.edu",
            "createdAt": "2020-05-01T07:15:45.952Z",
            "updatedAt": "2020-05-01T07:15:55.801Z",
            "tags": [],
            "classTitle": "cucumber_flower",
            "points": {
                "exterior": [
                    [
                        91,
                        370
                    ],
                    [
                        164,
                        429
                    ]
                ],
                "interior": []
            }
        },
        {
            "description": "",
            "geometryType": "rectangle",
            "labelerLogin": "ewwong2@dons.usfca.edu",
            "createdAt": "2020-05-01T07:15:52.555Z",
            "updatedAt": "2020-05-01T07:15:55.801Z",
            "tags": [],
            "classTitle": "cucumber_fruit",
            "points": {
                "exterior": [
                    [
                        1074,
                        0
                    ],
                    [
                        1205,
                        178
                    ]
                ],
                "interior": []
            }
        },
        {
            "description": "",
            "geometryType": "rectangle",
            "labelerLogin": "ewwong2@dons.usfca.edu",
            "createdAt": "2020-05-01T07:15:55.552Z",
            "updatedAt": "2020-05-01T07:15:55.552Z",
            "tags": [],
            "classTitle": "cucumber_fruit",
            "points": {
                "exterior": [
                    [
                        1175,
                        263
                    ],
                    [
                        1280,
                        512
                    ]
                ],
                "interior": []
            }
        }
    ]
}