{
    "description": "",
    "tags": [],
    "size": {
        "height": 720,
        "width": 1280
    },
    "objects": [
        {
            "description": "",
            "geometryType": "rectangle",
            "labelerLogin": "ewwong2@dons.usfca.edu",
            "createdAt": "2020-05-01T07:14:52.542Z",
            "updatedAt": "2020-05-01T07:15:02.969Z",
            "tags": [],
            "classTitle": "cucumber_flower",
            "points": {
                "exterior": [
                    [
                        498,
                        419
                    ],
                    [
                        596,
                        504
                    ]
                ],
                "interior": []
            }
        },
        {
            "description": "",
            "geometryType": "rectangle",
            "labelerLogin": "ewwong2@dons.usfca.edu",
            "createdAt": "2020-05-01T07:14:57.159Z",
            "updatedAt": "2020-05-01T07:15:02.969Z",
            "tags": [],
            "classTitle": "cucumber_fruit",
            "points": {
                "exterior": [
                    [
                        496,
                        285
                    ],
                    [
                        555,
                        407
                    ]
                ],
                "interior": []
            }
        },
        {
            "description": "",
            "geometryType": "rectangle",
            "labelerLogin": "ewwong2@dons.usfca.edu",
            "createdAt": "2020-05-01T07:14:59.467Z",
            "updatedAt": "2020-05-01T07:15:02.969Z",
            "tags": [],
            "classTitle": "cucumber_fruit",
            "points": {
                "exterior": [
                    [
                        0,
                        457
                    ],
                    [
                        268,
                        575
                    ]
                ],
                "interior": []
            }
        },
        {
            "description": "",
            "geometryType": "rectangle",
            "labelerLogin": "ewwong2@dons.usfca.edu",
            "createdAt": "2020-05-01T07:15:02.707Z",
            "updatedAt": "2020-05-01T07:15:02.707Z",
            "tags": [],
            "classTitle": "cucumber_flower",
            "points": {
                "exterior": [
                    [
                        284,
                        361
                    ],
                    [
                        350,
                        425
                    ]
                ],
                "interior": []
            }
        }
    ]
}