{
    "description": "",
    "tags": [],
    "size": {
        "height": 192,
        "width": 262
    },
    "objects": [
        {
            "description": "",
            "geometryType": "rectangle",
            "labelerLogin": "ksgill2",
            "createdAt": "2020-04-09T06:33:45.541Z",
            "updatedAt": "2020-04-09T06:34:16.363Z",
            "tags": [],
            "classTitle": "tomato_fruit_unripe",
            "points": {
                "exterior": [
                    [
                        132,
                        51
                    ],
                    [
                        156,
                        72
                    ]
                ],
                "interior": []
            }
        },
        {
            "description": "",
            "geometryType": "rectangle",
            "labelerLogin": "ksgill2",
            "createdAt": "2020-04-09T06:33:50.722Z",
            "updatedAt": "2020-04-09T06:34:16.363Z",
            "tags": [],
            "classTitle": "tomato_fruit",
            "points": {
                "exterior": [
                    [
                        112,
                        56
                    ],
                    [
                        137,
                        83
                    ]
                ],
                "interior": []
            }
        },
        {
            "description": "",
            "geometryType": "rectangle",
            "labelerLogin": "ksgill2",
            "createdAt": "2020-04-09T06:33:52.694Z",
            "updatedAt": "2020-04-09T06:34:16.363Z",
            "tags": [],
            "classTitle": "tomato_fruit",
            "points": {
                "exterior": [
                    [
                        96,
                        33
                    ],
                    [
                        124,
                        61
                    ]
                ],
                "interior": []
            }
        },
        {
            "description": "",
            "geometryType": "rectangle",
            "labelerLogin": "ksgill2",
            "createdAt": "2020-04-09T06:33:55.309Z",
            "updatedAt": "2020-04-09T06:34:16.363Z",
            "tags": [],
            "classTitle": "tomato_fruit",
            "points": {
                "exterior": [
                    [
                        91,
                        8
                    ],
                    [
                        119,
                        36
                    ]
                ],
                "interior": []
            }
        },
        {
            "description": "",
            "geometryType": "rectangle",
            "labelerLogin": "ksgill2",
            "createdAt": "2020-04-09T06:33:57.364Z",
            "updatedAt": "2020-04-09T06:34:16.363Z",
            "tags": [],
            "classTitle": "tomato_fruit",
            "points": {
                "exterior": [
                    [
                        122,
                        9
                    ],
                    [
                        141,
                        38
                    ]
                ],
                "interior": []
            }
        },
        {
            "description": "",
            "geometryType": "rectangle",
            "labelerLogin": "ksgill2",
            "createdAt": "2020-04-09T06:34:00.609Z",
            "updatedAt": "2020-04-09T06:34:16.363Z",
            "tags": [],
            "classTitle": "tomato_fruit",
            "points": {
                "exterior": [
                    [
                        83,
                        122
                    ],
                    [
                        110,
                        148
                    ]
                ],
                "interior": []
            }
        },
        {
            "description": "",
            "geometryType": "rectangle",
            "labelerLogin": "ksgill2",
            "createdAt": "2020-04-09T06:34:03.070Z",
            "updatedAt": "2020-04-09T06:34:16.363Z",
            "tags": [],
            "classTitle": "tomato_fruit",
            "points": {
                "exterior": [
                    [
                        77,
                        144
                    ],
                    [
                        104,
                        170
                    ]
                ],
                "interior": []
            }
        },
        {
            "description": "",
            "geometryType": "rectangle",
            "labelerLogin": "ksgill2",
            "createdAt": "2020-04-09T06:34:06.044Z",
            "updatedAt": "2020-04-09T06:34:16.363Z",
            "tags": [],
            "classTitle": "tomato_fruit",
            "points": {
                "exterior": [
                    [
                        59,
                        158
                    ],
                    [
                        80,
                        185
                    ]
                ],
                "interior": []
            }
        },
        {
            "description": "",
            "geometryType": "rectangle",
            "labelerLogin": "ksgill2",
            "createdAt": "2020-04-09T06:34:08.871Z",
            "updatedAt": "2020-04-09T06:34:16.363Z",
            "tags": [],
            "classTitle": "tomato_fruit",
            "points": {
                "exterior": [
                    [
                        39,
                        148
                    ],
                    [
                        62,
                        173
                    ]
                ],
                "interior": []
            }
        },
        {
            "description": "",
            "geometryType": "rectangle",
            "labelerLogin": "ksgill2",
            "createdAt": "2020-04-09T06:34:12.353Z",
            "updatedAt": "2020-04-09T06:34:16.363Z",
            "tags": [],
            "classTitle": "tomato_fruit",
            "points": {
                "exterior": [
                    [
                        171,
                        138
                    ],
                    [
                        203,
                        167
                    ]
                ],
                "interior": []
            }
        },
        {
            "description": "",
            "geometryType": "rectangle",
            "labelerLogin": "ksgill2",
            "createdAt": "2020-04-09T06:34:16.051Z",
            "updatedAt": "2020-04-09T06:34:19.685Z",
            "tags": [],
            "classTitle": "tomato_fruit",
            "points": {
                "exterior": [
                    [
                        192,
                        115
                    ],
                    [
                        227,
                        154
                    ]
                ],
                "interior": []
            }
        }
    ]
}