{
    "description": "",
    "tags": [],
    "size": {
        "height": 480,
        "width": 720
    },
    "objects": [
        {
            "description": "",
            "geometryType": "rectangle",
            "labelerLogin": "ksgill2",
            "createdAt": "2020-04-27T05:10:14.170Z",
            "updatedAt": "2020-04-27T05:10:27.995Z",
            "tags": [],
            "classTitle": "tomato_flower",
            "points": {
                "exterior": [
                    [
                        451,
                        25
                    ],
                    [
                        549,
                        117
                    ]
                ],
                "interior": []
            }
        },
        {
            "description": "",
            "geometryType": "rectangle",
            "labelerLogin": "ksgill2",
            "createdAt": "2020-04-27T05:10:16.675Z",
            "updatedAt": "2020-04-27T05:10:27.995Z",
            "tags": [],
            "classTitle": "tomato_flower",
            "points": {
                "exterior": [
                    [
                        385,
                        100
                    ],
                    [
                        464,
                        171
                    ]
                ],
                "interior": []
            }
        },
        {
            "description": "",
            "geometryType": "rectangle",
            "labelerLogin": "ksgill2",
            "createdAt": "2020-04-27T05:10:19.460Z",
            "updatedAt": "2020-04-27T05:10:27.995Z",
            "tags": [],
            "classTitle": "tomato_flower",
            "points": {
                "exterior": [
                    [
                        586,
                        324
                    ],
                    [
                        622,
                        390
                    ]
                ],
                "interior": []
            }
        },
        {
            "description": "",
            "geometryType": "rectangle",
            "labelerLogin": "ksgill2",
            "createdAt": "2020-04-27T05:10:21.507Z",
            "updatedAt": "2020-04-27T05:10:27.995Z",
            "tags": [],
            "classTitle": "tomato_flower",
            "points": {
                "exterior": [
                    [
                        653,
                        315
                    ],
                    [
                        692,
                        390
                    ]
                ],
                "interior": []
            }
        },
        {
            "description": "",
            "geometryType": "rectangle",
            "labelerLogin": "ksgill2",
            "createdAt": "2020-04-27T05:10:23.999Z",
            "updatedAt": "2020-04-27T05:10:27.995Z",
            "tags": [],
            "classTitle": "tomato_flower",
            "points": {
                "exterior": [
                    [
                        624,
                        182
                    ],
                    [
                        648,
                        233
                    ]
                ],
                "interior": []
            }
        },
        {
            "description": "",
            "geometryType": "rectangle",
            "labelerLogin": "ksgill2",
            "createdAt": "2020-04-27T05:10:27.527Z",
            "updatedAt": "2020-04-27T05:10:27.527Z",
            "tags": [],
            "classTitle": "tomato_flower",
            "points": {
                "exterior": [
                    [
                        597,
                        198
                    ],
                    [
                        624,
                        239
                    ]
                ],
                "interior": []
            }
        }
    ]
}