{
    "description": "",
    "tags": [],
    "size": {
        "height": 1024,
        "width": 576
    },
    "objects": [
        {
            "description": "",
            "geometryType": "rectangle",
            "labelerLogin": "simonl07",
            "createdAt": "2020-05-03T02:43:47.258Z",
            "updatedAt": "2020-05-03T02:44:12.684Z",
            "tags": [],
            "classTitle": "bell_pepper_young_plant",
            "points": {
                "exterior": [
                    [
                        0,
                        2
                    ],
                    [
                        576,
                        668
                    ]
                ],
                "interior": []
            }
        }
    ]
}