{
    "description": "",
    "tags": [],
    "size": {
        "height": 720,
        "width": 1280
    },
    "objects": [
        {
            "description": "",
            "geometryType": "rectangle",
            "labelerLogin": "ewwong2@dons.usfca.edu",
            "createdAt": "2020-04-10T03:08:17.805Z",
            "updatedAt": "2020-04-10T03:08:17.805Z",
            "tags": [],
            "classTitle": "cucumber_seedling",
            "points": {
                "exterior": [
                    [
                        343,
                        228
                    ],
                    [
                        610,
                        473
                    ]
                ],
                "interior": []
            }
        }
    ]
}